LICENSE
README.md
setup.py
NlpToolkit_PropBank.egg-info/PKG-INFO
NlpToolkit_PropBank.egg-info/SOURCES.txt
NlpToolkit_PropBank.egg-info/dependency_links.txt
NlpToolkit_PropBank.egg-info/top_level.txt
PropBank/Argument.py
PropBank/ArgumentList.py
PropBank/ArgumentType.py
PropBank/Frameset.py
PropBank/FramesetArgument.py
PropBank/FramesetList.py
PropBank/Predicate.py
PropBank/PredicateList.py
PropBank/Role.py
PropBank/RoleSet.py
PropBank/__init__.py
PropBank/data/__init__.py
PropBank/data/english-propbank.xml
PropBank/data/turkish-propbank.xml