Metadata-Version: 2.1
Name: NlpToolkit-PropBank
Version: 1.0.23
Summary: Turkish PropBank
Home-page: https://github.com/StarlangSoftware/TurkishPropbank-Py
Author: olcaytaner
Author-email: olcay.yildiz@ozyegin.edu.tr
License: UNKNOWN
Platform: UNKNOWN
